drf_addons_plus/__init__.py
drf_addons_plus/apps.py
drf_addons_plus/filters.py
drf_addons_plus/mixins.py
drf_addons_plus/models.py
drf_addons_plus/serializers.py
drf_addons_plus/tasks.py
drf_addons_plus/viewsets.py
drf_addons_plus/migrations/0001_initial.py
drf_addons_plus/migrations/__init__.py
drf_addons_plus-0.4.1.dist-info/LICENSE
drf_addons_plus-0.4.1.dist-info/METADATA
drf_addons_plus-0.4.1.dist-info/WHEEL
drf_addons_plus-0.4.1.dist-info/top_level.txt
drf_addons_plus-0.4.1.dist-info/RECORD
