Metadata-Version: 2.1
Name: drf_addons_plus
Version: 0.4.1
Summary: This project provides some extra functionalities to be used with Django REST Framework
Home-page: https://github.com/JGabrielGruber/drf-addons-plus
Author: José Gabriel Gruber
Author-email: development@jgabrielgruber.dev
License: AGPL-3.0
Classifier: Development Status :: 3 - Alpha
Classifier: Intended Audience :: Developers
Classifier: License :: OSI Approved :: MIT License
Classifier: Programming Language :: Python :: 3
Classifier: Programming Language :: Python :: 3.6
Classifier: Programming Language :: Python :: 3.7
Classifier: Programming Language :: Python :: 3.8
License-File: LICENSE
Requires-Dist: djangorestframework>=3.0
Requires-Dist: celery>=5.3
